django_graphql_countries-0.0.5.dist-info/DESCRIPTION.rst
django_graphql_countries-0.0.5.dist-info/METADATA
django_graphql_countries-0.0.5.dist-info/RECORD
django_graphql_countries-0.0.5.dist-info/WHEEL
django_graphql_countries-0.0.5.dist-info/metadata.json
django_graphql_countries-0.0.5.dist-info/top_level.txt
graphql_countries/__init__.py
graphql_countries/converter.py
graphql_countries/mixins.py
graphql_countries/queries.py
graphql_countries/types.py
graphql_countries/utils.py
graphql_countries/relay/__init__.py
graphql_countries/relay/lookups.py
graphql_countries/relay/nodes.py
graphql_countries/relay/queries.py
