Metadata-Version: 2.0
Name: django-graphql-countries
Version: 0.0.5
Summary: GraphQL implementation for countries
Home-page: https://github.com/flavors/django-graphql-countries/
Author: mongkok
Author-email: domake.io@gmail.com
License: MIT
Platform: UNKNOWN
Classifier: Development Status :: 1 - Planning
Classifier: Environment :: Web Environment
Classifier: Intended Audience :: Developers
Classifier: License :: OSI Approved :: MIT License
Classifier: Operating System :: OS Independent
Classifier: Programming Language :: Python
Classifier: Programming Language :: Python :: 3
Classifier: Programming Language :: Python :: 3.4
Classifier: Programming Language :: Python :: 3.5
Classifier: Programming Language :: Python :: 3.6
Classifier: Programming Language :: Python :: 3.7
Classifier: Framework :: Django
Requires-Dist: Django (>=1.11)
Requires-Dist: django-countries-flavor (>=0.0.8)
Requires-Dist: graphene-django (>=2.0.0)
